qt_echarts-0.0.3.data/data/requirements.txt
qtecharts/__init__.py
qtecharts/charts_engine.py
qtecharts/test.py
qtecharts/utils/__init__.py
qtecharts/utils/chart_chanel.py
qt_echarts-0.0.3.dist-info/METADATA
qt_echarts-0.0.3.dist-info/WHEEL
qt_echarts-0.0.3.dist-info/top_level.txt
qt_echarts-0.0.3.dist-info/RECORD
