Metadata-Version: 2.1
Name: qt-echarts
Version: 0.0.3
Summary: pyqt-echarts 通过QWebEngine和pyecharts进行处理
Home-page: https://pypi.org/project/qt-echarts/
Author: SiberianHusky
Author-email: 3088506834@qq.com
Classifier: Programming Language :: Python :: 3
Classifier: License :: OSI Approved :: MIT License
Classifier: Operating System :: OS Independent
Requires-Python: >=3.8
Requires-Dist: beautifulsoup4
Requires-Dist: lxml
Requires-Dist: pyecharts
Requires-Dist: PyQt5
Requires-Dist: PyQt5-sip
Requires-Dist: PyQtWebEngine
